method_override/__init__.py
method_override/wsgi_method_override.py
method_override-0.3.0.dist-info/LICENSE
method_override-0.3.0.dist-info/METADATA
method_override-0.3.0.dist-info/WHEEL
method_override-0.3.0.dist-info/RECORD
