Metadata-Version: 2.3
Name: method-override
Version: 0.3.0
Summary: A Python WSGI middleware for HTTP method override functionality
License: MIT
Keywords: wsgi,web server,method override,http,middleware
Author: Marcus Almeida
Author-email: mpereirassa@gmail.com
Requires-Python: >=3.10.0
Classifier: License :: OSI Approved :: MIT License
Classifier: Programming Language :: Python :: 3
Classifier: Programming Language :: Python :: 3.10
Classifier: Programming Language :: Python :: 3.11
Classifier: Programming Language :: Python :: 3.12
Classifier: Programming Language :: Python :: 3.13
